<?xml version="1.0" encoding="UTF-8"?>
<beans xmlns="http://www.springframework.org/schema/beans"
       xmlns:xsi="http://www.w3.org/2001/XMLSchema-instance"
       xsi:schemaLocation="
           http://www.springframework.org/schema/beans
           http://www.springframework.org/schema/beans/spring-beans-4.0.xsd">

  <bean id="daemonMgr" class="org.opennms.netmgt.vmmgr.DaemonManagerDefault">
    <property name="serviceDaemons"><ref bean="serviceDaemons"/></property> 
  </bean>
  
  <bean id="exporter" class="org.springframework.remoting.rmi.RmiServiceExporter">
		<!-- does not necessarily have to be the same name as the bean to be exported -->	
		<property name="serviceName" value="daemonMgr"/>
		<property name="service" ref="daemonMgr"/>
		<property name="serviceInterface" value="org.opennms.netmgt.vmmgr.DaemonManager"/>	
		<!-- defaults to 1099 
		<property name="registryPort" value="1199"/>
		-->
	</bean>
  
  <!--
    this bean needs to be eagerly pre-instantiated in order for the exporting to occur;
    this means that it must not be marked as lazily initialized
  <bean id="exporter" class="org.springframework.jmx.export.MBeanExporter" lazy-init="false">
    <property name="beans">
       <map>
         <entry key="OpenNMS:DaemonManager=true" value-ref="daemonMgr-local"/>
       </map>
    </property>
    <property name="server" ref="mbeanServer"/>
  </bean>
  
  <bean id="serverConnector" class="org.springframework.jmx.support.ConnectorServerFactoryBean"/>
  
  <bean id="clientConnector" class="org.springframework.jmx.support.MBeanServerConnectionFactoryBean">
	  <property name="serviceUrl" value="service:jmx:jmxmp://localhost:9875"/>
	</bean>

	<bean id="daemonMgr-remote" class="org.springframework.jmx.access.MBeanProxyFactoryBean">
	  <property name="objectName" value="OpenNMS:DaemonManager=true"/>
	  <property name="proxyInterface" value="org.opennms.netmgt.vmmgr.DaemonManager"/>
	  <property name="server" ref="clientConnector"/>
	</bean>
  -->

</beans>
