<events xmlns="http://xmlns.opennms.org/xsd/eventconf">
   <event>
      <mask>
         <maskelement>
            <mename>id</mename>
            <mevalue>.1.3.6.1.4.1.14823.2.2.1.1.100</mevalue>
         </maskelement>
         <maskelement>
            <mename>generic</mename>
            <mevalue>6</mevalue>
         </maskelement>
         <maskelement>
            <mename>specific</mename>
            <mevalue>1001</mevalue>
         </maskelement>
      </mask>
      <uei>uei.opennms.org/vendor/aruba/switch/traps/wlsxSwitchIPChanged</uei>
      <event-label>WLSX-SWITCH-MIB defined trap event: wlsxSwitchIPChanged</event-label>
      <descr>&lt;p>A trap which indicates that the switch IP address has changed.&lt;/p>&lt;table>
	&lt;tr>&lt;td>&lt;b>

	wlsxSwitchIp&lt;/b>&lt;/td>&lt;td>
	%parm[#1]%;&lt;/td>&lt;td>&lt;p>&lt;/p>&lt;/td>&lt;/tr>&lt;/table></descr>
      <logmsg dest="logndisplay">&lt;p>
	wlsxSwitchIPChanged trap received
	wlsxSwitchIp=%parm[#1]%&lt;/p></logmsg>
      <severity>Indeterminate</severity>
   </event>
   <event>
      <mask>
         <maskelement>
            <mename>id</mename>
            <mevalue>.1.3.6.1.4.1.14823.2.2.1.1.100</mevalue>
         </maskelement>
         <maskelement>
            <mename>generic</mename>
            <mevalue>6</mevalue>
         </maskelement>
         <maskelement>
            <mename>specific</mename>
            <mevalue>1002</mevalue>
         </maskelement>
      </mask>
      <uei>uei.opennms.org/vendor/aruba/switch/traps/wlsxSwitchRoleChange</uei>
      <event-label>WLSX-SWITCH-MIB defined trap event: wlsxSwitchRoleChange</event-label>
      <descr>&lt;p>A trap which indicates that the role of the switch has changed in 
			the Domain.&lt;/p>&lt;table>
	&lt;tr>&lt;td>&lt;b>

	wlsxSwitchRole&lt;/b>&lt;/td>&lt;td>
	%parm[#1]%;&lt;/td>&lt;td>&lt;p>
		master(1)
		local(2)
		standbymaster(3)
	&lt;/p>&lt;/td>&lt;/tr>&lt;/table></descr>
      <logmsg dest="logndisplay">&lt;p>
	wlsxSwitchRoleChange trap received
	wlsxSwitchRole=%parm[#1]%&lt;/p></logmsg>
      <severity>Indeterminate</severity>
      <varbindsdecode>
         <parmid>parm[#1]</parmid>
         <decode varbindvalue="1" varbinddecodedstring="master"/>
         <decode varbindvalue="2" varbinddecodedstring="local"/>
         <decode varbindvalue="3" varbinddecodedstring="standbymaster"/>
      </varbindsdecode>
   </event>
   <event>
      <mask>
         <maskelement>
            <mename>id</mename>
            <mevalue>.1.3.6.1.4.1.14823.2.2.1.1.100</mevalue>
         </maskelement>
         <maskelement>
            <mename>generic</mename>
            <mevalue>6</mevalue>
         </maskelement>
         <maskelement>
            <mename>specific</mename>
            <mevalue>1003</mevalue>
         </maskelement>
      </mask>
      <uei>uei.opennms.org/vendor/aruba/switch/traps/wlsxUserEntryCreated</uei>
      <event-label>WLSX-SWITCH-MIB defined trap event: wlsxUserEntryCreated</event-label>
      <descr>&lt;p>
			A trap which indicates that a New user is created.
			&lt;/p>&lt;table>
	&lt;tr>&lt;td>&lt;b>

	userPhyAddress&lt;/b>&lt;/td>&lt;td>
	%parm[#1]%;&lt;/td>&lt;td>&lt;p>&lt;/p>&lt;/td>&lt;/tr>&lt;/table></descr>
      <logmsg dest="logndisplay">&lt;p>
	wlsxUserEntryCreated trap received
	userPhyAddress=%parm[#1]%&lt;/p></logmsg>
      <severity>Indeterminate</severity>
   </event>
   <event>
      <mask>
         <maskelement>
            <mename>id</mename>
            <mevalue>.1.3.6.1.4.1.14823.2.2.1.1.100</mevalue>
         </maskelement>
         <maskelement>
            <mename>generic</mename>
            <mevalue>6</mevalue>
         </maskelement>
         <maskelement>
            <mename>specific</mename>
            <mevalue>1004</mevalue>
         </maskelement>
      </mask>
      <uei>uei.opennms.org/vendor/aruba/switch/traps/wlsxUserEntryDeleted</uei>
      <event-label>WLSX-SWITCH-MIB defined trap event: wlsxUserEntryDeleted</event-label>
      <descr>&lt;p>
			A trap which indicates that a user is deleted.
			&lt;/p>&lt;table>
	&lt;tr>&lt;td>&lt;b>

	userPhyAddress&lt;/b>&lt;/td>&lt;td>
	%parm[#1]%;&lt;/td>&lt;td>&lt;p>&lt;/p>&lt;/td>&lt;/tr>&lt;/table></descr>
      <logmsg dest="logndisplay">&lt;p>
	wlsxUserEntryDeleted trap received
	userPhyAddress=%parm[#1]%&lt;/p></logmsg>
      <severity>Indeterminate</severity>
   </event>
   <event>
      <mask>
         <maskelement>
            <mename>id</mename>
            <mevalue>.1.3.6.1.4.1.14823.2.2.1.1.100</mevalue>
         </maskelement>
         <maskelement>
            <mename>generic</mename>
            <mevalue>6</mevalue>
         </maskelement>
         <maskelement>
            <mename>specific</mename>
            <mevalue>1005</mevalue>
         </maskelement>
      </mask>
      <uei>uei.opennms.org/vendor/aruba/switch/traps/wlsxUserEntryAuthenticated</uei>
      <event-label>WLSX-SWITCH-MIB defined trap event: wlsxUserEntryAuthenticated</event-label>
      <descr>&lt;p>
			A trap which indicates that a user is Authenticated.
			&lt;/p>&lt;table>
	&lt;tr>&lt;td>&lt;b>

	userPhyAddress&lt;/b>&lt;/td>&lt;td>
	%parm[#1]%;&lt;/td>&lt;td>&lt;p>&lt;/p>&lt;/td>&lt;/tr>
	&lt;tr>&lt;td>&lt;b>

	userName&lt;/b>&lt;/td>&lt;td>
	%parm[#2]%;&lt;/td>&lt;td>&lt;p>&lt;/p>&lt;/td>&lt;/tr>
	&lt;tr>&lt;td>&lt;b>

	userAuthenticationMethod&lt;/b>&lt;/td>&lt;td>
	%parm[#3]%;&lt;/td>&lt;td>&lt;p>
		none(1)
		other(2)
		web(3)
		dot1x(4)
		vpn(5)
		mac(6)
	&lt;/p>&lt;/td>&lt;/tr>
	&lt;tr>&lt;td>&lt;b>

	userRole&lt;/b>&lt;/td>&lt;td>
	%parm[#4]%;&lt;/td>&lt;td>&lt;p>&lt;/p>&lt;/td>&lt;/tr>&lt;/table></descr>
      <logmsg dest="logndisplay">&lt;p>
	wlsxUserEntryAuthenticated trap received
	userPhyAddress=%parm[#1]%
	userName=%parm[#2]%
	userAuthenticationMethod=%parm[#3]%
	userRole=%parm[#4]%&lt;/p></logmsg>
      <severity>Indeterminate</severity>
      <varbindsdecode>
         <parmid>parm[#3]</parmid>
         <decode varbindvalue="1" varbinddecodedstring="none"/>
         <decode varbindvalue="2" varbinddecodedstring="other"/>
         <decode varbindvalue="3" varbinddecodedstring="web"/>
         <decode varbindvalue="4" varbinddecodedstring="dot1x"/>
         <decode varbindvalue="5" varbinddecodedstring="vpn"/>
         <decode varbindvalue="6" varbinddecodedstring="mac"/>
      </varbindsdecode>
   </event>
   <event>
      <mask>
         <maskelement>
            <mename>id</mename>
            <mevalue>.1.3.6.1.4.1.14823.2.2.1.1.100</mevalue>
         </maskelement>
         <maskelement>
            <mename>generic</mename>
            <mevalue>6</mevalue>
         </maskelement>
         <maskelement>
            <mename>specific</mename>
            <mevalue>1006</mevalue>
         </maskelement>
      </mask>
      <uei>uei.opennms.org/vendor/aruba/switch/traps/wlsxUserEntryDeAuthenticated</uei>
      <event-label>WLSX-SWITCH-MIB defined trap event: wlsxUserEntryDeAuthenticated</event-label>
      <descr>&lt;p>
			A trap which indicates that a user is Deauthenticated.
			&lt;/p>&lt;table>
	&lt;tr>&lt;td>&lt;b>

	userPhyAddress&lt;/b>&lt;/td>&lt;td>
	%parm[#1]%;&lt;/td>&lt;td>&lt;p>&lt;/p>&lt;/td>&lt;/tr>&lt;/table></descr>
      <logmsg dest="logndisplay">&lt;p>
	wlsxUserEntryDeAuthenticated trap received
	userPhyAddress=%parm[#1]%&lt;/p></logmsg>
      <severity>Indeterminate</severity>
   </event>
   <event>
      <mask>
         <maskelement>
            <mename>id</mename>
            <mevalue>.1.3.6.1.4.1.14823.2.2.1.1.100</mevalue>
         </maskelement>
         <maskelement>
            <mename>generic</mename>
            <mevalue>6</mevalue>
         </maskelement>
         <maskelement>
            <mename>specific</mename>
            <mevalue>1007</mevalue>
         </maskelement>
      </mask>
      <uei>uei.opennms.org/vendor/aruba/switch/traps/wlsxUserAuthenticationFailed</uei>
      <event-label>WLSX-SWITCH-MIB defined trap event: wlsxUserAuthenticationFailed</event-label>
      <descr>&lt;p>
			A trap which indicates that a user authentication has failed.
			&lt;/p>&lt;table>
	&lt;tr>&lt;td>&lt;b>

	userPhyAddress&lt;/b>&lt;/td>&lt;td>
	%parm[#1]%;&lt;/td>&lt;td>&lt;p>&lt;/p>&lt;/td>&lt;/tr>&lt;/table></descr>
      <logmsg dest="logndisplay">&lt;p>
	wlsxUserAuthenticationFailed trap received
	userPhyAddress=%parm[#1]%&lt;/p></logmsg>
      <severity>Indeterminate</severity>
   </event>
   <event>
      <mask>
         <maskelement>
            <mename>id</mename>
            <mevalue>.1.3.6.1.4.1.14823.2.2.1.1.100</mevalue>
         </maskelement>
         <maskelement>
            <mename>generic</mename>
            <mevalue>6</mevalue>
         </maskelement>
         <maskelement>
            <mename>specific</mename>
            <mevalue>1008</mevalue>
         </maskelement>
      </mask>
      <uei>uei.opennms.org/vendor/aruba/switch/traps/wlsxAuthServerReqTimedOut</uei>
      <event-label>WLSX-SWITCH-MIB defined trap event: wlsxAuthServerReqTimedOut</event-label>
      <descr>&lt;p>
			A trap which indicates that the authentication server request 
			timed out.
			&lt;/p>&lt;table>
	&lt;tr>&lt;td>&lt;b>

	wlsxAuthServerName&lt;/b>&lt;/td>&lt;td>
	%parm[#1]%;&lt;/td>&lt;td>&lt;p>&lt;/p>&lt;/td>&lt;/tr>&lt;/table></descr>
      <logmsg dest="logndisplay">&lt;p>
	wlsxAuthServerReqTimedOut trap received
	wlsxAuthServerName=%parm[#1]%&lt;/p></logmsg>
      <severity>Indeterminate</severity>
   </event>
   <event>
      <mask>
         <maskelement>
            <mename>id</mename>
            <mevalue>.1.3.6.1.4.1.14823.2.2.1.1.100</mevalue>
         </maskelement>
         <maskelement>
            <mename>generic</mename>
            <mevalue>6</mevalue>
         </maskelement>
         <maskelement>
            <mename>specific</mename>
            <mevalue>1009</mevalue>
         </maskelement>
      </mask>
      <uei>uei.opennms.org/vendor/aruba/switch/traps/wlsxAuthServerTimedOut</uei>
      <event-label>WLSX-SWITCH-MIB defined trap event: wlsxAuthServerTimedOut</event-label>
      <descr>&lt;p>
			A trap which indicates that the authentication server 
			timed out.
			&lt;/p>&lt;table>
	&lt;tr>&lt;td>&lt;b>

	wlsxAuthServerName&lt;/b>&lt;/td>&lt;td>
	%parm[#1]%;&lt;/td>&lt;td>&lt;p>&lt;/p>&lt;/td>&lt;/tr>
	&lt;tr>&lt;td>&lt;b>

	wlsxAuthServerTimeout&lt;/b>&lt;/td>&lt;td>
	%parm[#2]%;&lt;/td>&lt;td>&lt;p>&lt;/p>&lt;/td>&lt;/tr>&lt;/table></descr>
      <logmsg dest="logndisplay">&lt;p>
	wlsxAuthServerTimedOut trap received
	wlsxAuthServerName=%parm[#1]%
	wlsxAuthServerTimeout=%parm[#2]%&lt;/p></logmsg>
      <severity>Indeterminate</severity>
   </event>
   <event>
      <mask>
         <maskelement>
            <mename>id</mename>
            <mevalue>.1.3.6.1.4.1.14823.2.2.1.1.100</mevalue>
         </maskelement>
         <maskelement>
            <mename>generic</mename>
            <mevalue>6</mevalue>
         </maskelement>
         <maskelement>
            <mename>specific</mename>
            <mevalue>1010</mevalue>
         </maskelement>
      </mask>
      <uei>uei.opennms.org/vendor/aruba/switch/traps/wlsxAuthServerIsUp</uei>
      <event-label>WLSX-SWITCH-MIB defined trap event: wlsxAuthServerIsUp</event-label>
      <descr>&lt;p>
			A trap which indicates that the authentication server is up.
			&lt;/p>&lt;table>
	&lt;tr>&lt;td>&lt;b>

	wlsxAuthServerName&lt;/b>&lt;/td>&lt;td>
	%parm[#1]%;&lt;/td>&lt;td>&lt;p>&lt;/p>&lt;/td>&lt;/tr>&lt;/table></descr>
      <logmsg dest="logndisplay">&lt;p>
	wlsxAuthServerIsUp trap received
	wlsxAuthServerName=%parm[#1]%&lt;/p></logmsg>
      <severity>Indeterminate</severity>
   </event>
   <event>
      <mask>
         <maskelement>
            <mename>id</mename>
            <mevalue>.1.3.6.1.4.1.14823.2.2.1.1.100</mevalue>
         </maskelement>
         <maskelement>
            <mename>generic</mename>
            <mevalue>6</mevalue>
         </maskelement>
         <maskelement>
            <mename>specific</mename>
            <mevalue>1011</mevalue>
         </maskelement>
      </mask>
      <uei>uei.opennms.org/vendor/aruba/switch/traps/wlsxAuthMaxUserEntries</uei>
      <event-label>WLSX-SWITCH-MIB defined trap event: wlsxAuthMaxUserEntries</event-label>
      <descr>&lt;p>
			A trap which indicates that the User Entries table is full and
			cannot add any more entries.
			&lt;/p>&lt;table>&lt;/table></descr>
      <logmsg dest="logndisplay">&lt;p>
	wlsxAuthMaxUserEntries trap received&lt;/p></logmsg>
      <severity>Indeterminate</severity>
   </event>
   <event>
      <mask>
         <maskelement>
            <mename>id</mename>
            <mevalue>.1.3.6.1.4.1.14823.2.2.1.1.100</mevalue>
         </maskelement>
         <maskelement>
            <mename>generic</mename>
            <mevalue>6</mevalue>
         </maskelement>
         <maskelement>
            <mename>specific</mename>
            <mevalue>1012</mevalue>
         </maskelement>
      </mask>
      <uei>uei.opennms.org/vendor/aruba/switch/traps/wlsxAuthMaxAclEntries</uei>
      <event-label>WLSX-SWITCH-MIB defined trap event: wlsxAuthMaxAclEntries</event-label>
      <descr>&lt;p>
			A trap which indicates that the Acl Entries table is full and
			cannot add any more entries.
			&lt;/p>&lt;table>&lt;/table></descr>
      <logmsg dest="logndisplay">&lt;p>
	wlsxAuthMaxAclEntries trap received&lt;/p></logmsg>
      <severity>Indeterminate</severity>
   </event>
   <event>
      <mask>
         <maskelement>
            <mename>id</mename>
            <mevalue>.1.3.6.1.4.1.14823.2.2.1.1.100</mevalue>
         </maskelement>
         <maskelement>
            <mename>generic</mename>
            <mevalue>6</mevalue>
         </maskelement>
         <maskelement>
            <mename>specific</mename>
            <mevalue>1013</mevalue>
         </maskelement>
      </mask>
      <uei>uei.opennms.org/vendor/aruba/switch/traps/wlsxAuthMaxBWContracts</uei>
      <event-label>WLSX-SWITCH-MIB defined trap event: wlsxAuthMaxBWContracts</event-label>
      <descr>&lt;p>
			A trap which indicates that the switch reached the maximum number of
			configurable Bandwidth contracts.
			&lt;/p>&lt;table>&lt;/table></descr>
      <logmsg dest="logndisplay">&lt;p>
	wlsxAuthMaxBWContracts trap received&lt;/p></logmsg>
      <severity>Indeterminate</severity>
   </event>
   <event>
      <mask>
         <maskelement>
            <mename>id</mename>
            <mevalue>.1.3.6.1.4.1.14823.2.2.1.1.100</mevalue>
         </maskelement>
         <maskelement>
            <mename>generic</mename>
            <mevalue>6</mevalue>
         </maskelement>
         <maskelement>
            <mename>specific</mename>
            <mevalue>1014</mevalue>
         </maskelement>
      </mask>
      <uei>uei.opennms.org/vendor/aruba/switch/traps/wlsxPowerSupplyFailure</uei>
      <event-label>WLSX-SWITCH-MIB defined trap event: wlsxPowerSupplyFailure</event-label>
      <descr>&lt;p>
			A trap which indicates that the power supply has failed.
			&lt;/p>&lt;table>&lt;/table></descr>
      <logmsg dest="logndisplay">&lt;p>
	wlsxPowerSupplyFailure trap received&lt;/p></logmsg>
      <severity>Indeterminate</severity>
   </event>
   <event>
      <mask>
         <maskelement>
            <mename>id</mename>
            <mevalue>.1.3.6.1.4.1.14823.2.2.1.1.100</mevalue>
         </maskelement>
         <maskelement>
            <mename>generic</mename>
            <mevalue>6</mevalue>
         </maskelement>
         <maskelement>
            <mename>specific</mename>
            <mevalue>1015</mevalue>
         </maskelement>
      </mask>
      <uei>uei.opennms.org/vendor/aruba/switch/traps/wlsxFanFailure</uei>
      <event-label>WLSX-SWITCH-MIB defined trap event: wlsxFanFailure</event-label>
      <descr>&lt;p>
			A trap which indicates that the fan has failed.
			&lt;/p>&lt;table>
	&lt;tr>&lt;td>&lt;b>

	wlsxFanNumber&lt;/b>&lt;/td>&lt;td>
	%parm[#1]%;&lt;/td>&lt;td>&lt;p>&lt;/p>&lt;/td>&lt;/tr>&lt;/table></descr>
      <logmsg dest="logndisplay">&lt;p>
	wlsxFanFailure trap received
	wlsxFanNumber=%parm[#1]%&lt;/p></logmsg>
      <severity>Indeterminate</severity>
   </event>
   <event>
      <mask>
         <maskelement>
            <mename>id</mename>
            <mevalue>.1.3.6.1.4.1.14823.2.2.1.1.100</mevalue>
         </maskelement>
         <maskelement>
            <mename>generic</mename>
            <mevalue>6</mevalue>
         </maskelement>
         <maskelement>
            <mename>specific</mename>
            <mevalue>1016</mevalue>
         </maskelement>
      </mask>
      <uei>uei.opennms.org/vendor/aruba/switch/traps/wlsxOutOfRangeVoltage</uei>
      <event-label>WLSX-SWITCH-MIB defined trap event: wlsxOutOfRangeVoltage</event-label>
      <descr>&lt;p>
			A trap which indicates that the switch received out of range 
			voltage.
			&lt;/p>&lt;table>
	&lt;tr>&lt;td>&lt;b>

	wlsxVoltageType&lt;/b>&lt;/td>&lt;td>
	%parm[#1]%;&lt;/td>&lt;td>&lt;p>&lt;/p>&lt;/td>&lt;/tr>
	&lt;tr>&lt;td>&lt;b>

	wlsxVoltageValue&lt;/b>&lt;/td>&lt;td>
	%parm[#2]%;&lt;/td>&lt;td>&lt;p>&lt;/p>&lt;/td>&lt;/tr>&lt;/table></descr>
      <logmsg dest="logndisplay">&lt;p>
	wlsxOutOfRangeVoltage trap received
	wlsxVoltageType=%parm[#1]%
	wlsxVoltageValue=%parm[#2]%&lt;/p></logmsg>
      <severity>Indeterminate</severity>
   </event>
   <event>
      <mask>
         <maskelement>
            <mename>id</mename>
            <mevalue>.1.3.6.1.4.1.14823.2.2.1.1.100</mevalue>
         </maskelement>
         <maskelement>
            <mename>generic</mename>
            <mevalue>6</mevalue>
         </maskelement>
         <maskelement>
            <mename>specific</mename>
            <mevalue>1017</mevalue>
         </maskelement>
      </mask>
      <uei>uei.opennms.org/vendor/aruba/switch/traps/wlsxOutOfRangeTemperature</uei>
      <event-label>WLSX-SWITCH-MIB defined trap event: wlsxOutOfRangeTemperature</event-label>
      <descr>&lt;p>
			A trap which indicates that the Temperature is out of bounds.
			&lt;/p>&lt;table>
	&lt;tr>&lt;td>&lt;b>

	wlsxTemperatureValue&lt;/b>&lt;/td>&lt;td>
	%parm[#1]%;&lt;/td>&lt;td>&lt;p>&lt;/p>&lt;/td>&lt;/tr>&lt;/table></descr>
      <logmsg dest="logndisplay">&lt;p>
	wlsxOutOfRangeTemperature trap received
	wlsxTemperatureValue=%parm[#1]%&lt;/p></logmsg>
      <severity>Indeterminate</severity>
   </event>
   <event>
      <mask>
         <maskelement>
            <mename>id</mename>
            <mevalue>.1.3.6.1.4.1.14823.2.2.1.1.100</mevalue>
         </maskelement>
         <maskelement>
            <mename>generic</mename>
            <mevalue>6</mevalue>
         </maskelement>
         <maskelement>
            <mename>specific</mename>
            <mevalue>1018</mevalue>
         </maskelement>
      </mask>
      <uei>uei.opennms.org/vendor/aruba/switch/traps/wlsxLCInserted</uei>
      <event-label>WLSX-SWITCH-MIB defined trap event: wlsxLCInserted</event-label>
      <descr>&lt;p>
			A trap which indicates that a Line card is inserted.
			&lt;/p>&lt;table>
	&lt;tr>&lt;td>&lt;b>

	wlsxLineCardNumber&lt;/b>&lt;/td>&lt;td>
	%parm[#1]%;&lt;/td>&lt;td>&lt;p>&lt;/p>&lt;/td>&lt;/tr>
	&lt;tr>&lt;td>&lt;b>

	wlsxSlotNumber&lt;/b>&lt;/td>&lt;td>
	%parm[#2]%;&lt;/td>&lt;td>&lt;p>&lt;/p>&lt;/td>&lt;/tr>&lt;/table></descr>
      <logmsg dest="logndisplay">&lt;p>
	wlsxLCInserted trap received
	wlsxLineCardNumber=%parm[#1]%
	wlsxSlotNumber=%parm[#2]%&lt;/p></logmsg>
      <severity>Indeterminate</severity>
   </event>
   <event>
      <mask>
         <maskelement>
            <mename>id</mename>
            <mevalue>.1.3.6.1.4.1.14823.2.2.1.1.100</mevalue>
         </maskelement>
         <maskelement>
            <mename>generic</mename>
            <mevalue>6</mevalue>
         </maskelement>
         <maskelement>
            <mename>specific</mename>
            <mevalue>1019</mevalue>
         </maskelement>
      </mask>
      <uei>uei.opennms.org/vendor/aruba/switch/traps/wlsxSCInserted</uei>
      <event-label>WLSX-SWITCH-MIB defined trap event: wlsxSCInserted</event-label>
      <descr>&lt;p>
			A trap which indicates that a supervisory card is inserted.
			&lt;/p>&lt;table>&lt;/table></descr>
      <logmsg dest="logndisplay">&lt;p>
	wlsxSCInserted trap received&lt;/p></logmsg>
      <severity>Indeterminate</severity>
   </event>
   <event>
      <mask>
         <maskelement>
            <mename>id</mename>
            <mevalue>.1.3.6.1.4.1.14823.2.2.1.1.100</mevalue>
         </maskelement>
         <maskelement>
            <mename>generic</mename>
            <mevalue>6</mevalue>
         </maskelement>
         <maskelement>
            <mename>specific</mename>
            <mevalue>1020</mevalue>
         </maskelement>
      </mask>
      <uei>uei.opennms.org/vendor/aruba/switch/traps/wlsxGBICInserted</uei>
      <event-label>WLSX-SWITCH-MIB defined trap event: wlsxGBICInserted</event-label>
      <descr>&lt;p>
			A trap which indicates that a GBIC is inserted in a line card. 
			&lt;/p>&lt;table>&lt;/table></descr>
      <logmsg dest="logndisplay">&lt;p>
	wlsxGBICInserted trap received&lt;/p></logmsg>
      <severity>Indeterminate</severity>
   </event>
   <event>
      <mask>
         <maskelement>
            <mename>id</mename>
            <mevalue>.1.3.6.1.4.1.14823.2.2.1.1.100</mevalue>
         </maskelement>
         <maskelement>
            <mename>generic</mename>
            <mevalue>6</mevalue>
         </maskelement>
         <maskelement>
            <mename>specific</mename>
            <mevalue>1021</mevalue>
         </maskelement>
      </mask>
      <uei>uei.opennms.org/vendor/aruba/switch/traps/wlsxProcessDied</uei>
      <event-label>WLSX-SWITCH-MIB defined trap event: wlsxProcessDied</event-label>
      <descr>&lt;p>
			A trap which indicates that a process has died.
			&lt;/p>&lt;table>
	&lt;tr>&lt;td>&lt;b>

	wlsxProcessName&lt;/b>&lt;/td>&lt;td>
	%parm[#1]%;&lt;/td>&lt;td>&lt;p>&lt;/p>&lt;/td>&lt;/tr>&lt;/table></descr>
      <logmsg dest="logndisplay">&lt;p>
	wlsxProcessDied trap received
	wlsxProcessName=%parm[#1]%&lt;/p></logmsg>
      <severity>Indeterminate</severity>
   </event>
   <event>
      <mask>
         <maskelement>
            <mename>id</mename>
            <mevalue>.1.3.6.1.4.1.14823.2.2.1.1.100</mevalue>
         </maskelement>
         <maskelement>
            <mename>generic</mename>
            <mevalue>6</mevalue>
         </maskelement>
         <maskelement>
            <mename>specific</mename>
            <mevalue>1022</mevalue>
         </maskelement>
      </mask>
      <uei>uei.opennms.org/vendor/aruba/switch/traps/wlsxProcessExceedsMemoryLimits</uei>
      <event-label>WLSX-SWITCH-MIB defined trap event: wlsxProcessExceedsMemoryLimits</event-label>
      <descr>&lt;p>
			A trap which indicates that a process is consuming large
			amounts of memory.
			&lt;/p>&lt;table>
	&lt;tr>&lt;td>&lt;b>

	wlsxProcessName&lt;/b>&lt;/td>&lt;td>
	%parm[#1]%;&lt;/td>&lt;td>&lt;p>&lt;/p>&lt;/td>&lt;/tr>&lt;/table></descr>
      <logmsg dest="logndisplay">&lt;p>
	wlsxProcessExceedsMemoryLimits trap received
	wlsxProcessName=%parm[#1]%&lt;/p></logmsg>
      <severity>Indeterminate</severity>
   </event>
   <event>
      <mask>
         <maskelement>
            <mename>id</mename>
            <mevalue>.1.3.6.1.4.1.14823.2.2.1.1.100</mevalue>
         </maskelement>
         <maskelement>
            <mename>generic</mename>
            <mevalue>6</mevalue>
         </maskelement>
         <maskelement>
            <mename>specific</mename>
            <mevalue>1023</mevalue>
         </maskelement>
      </mask>
      <uei>uei.opennms.org/vendor/aruba/switch/traps/wlsxLowOnFlashSpace</uei>
      <event-label>WLSX-SWITCH-MIB defined trap event: wlsxLowOnFlashSpace</event-label>
      <descr>&lt;p>
			A trap which indicates that the switch is running low on flash space.
			&lt;/p>&lt;table>&lt;/table></descr>
      <logmsg dest="logndisplay">&lt;p>
	wlsxLowOnFlashSpace trap received&lt;/p></logmsg>
      <severity>Indeterminate</severity>
   </event>
   <event>
      <mask>
         <maskelement>
            <mename>id</mename>
            <mevalue>.1.3.6.1.4.1.14823.2.2.1.1.100</mevalue>
         </maskelement>
         <maskelement>
            <mename>generic</mename>
            <mevalue>6</mevalue>
         </maskelement>
         <maskelement>
            <mename>specific</mename>
            <mevalue>1024</mevalue>
         </maskelement>
      </mask>
      <uei>uei.opennms.org/vendor/aruba/switch/traps/wlsxLowMemory</uei>
      <event-label>WLSX-SWITCH-MIB defined trap event: wlsxLowMemory</event-label>
      <descr>&lt;p>
			A trap which indicates that the system free memory is low.
			&lt;/p>&lt;table>&lt;/table></descr>
      <logmsg dest="logndisplay">&lt;p>
	wlsxLowMemory trap received&lt;/p></logmsg>
      <severity>Indeterminate</severity>
   </event>
   <event>
      <mask>
         <maskelement>
            <mename>id</mename>
            <mevalue>.1.3.6.1.4.1.14823.2.2.1.1.100</mevalue>
         </maskelement>
         <maskelement>
            <mename>generic</mename>
            <mevalue>6</mevalue>
         </maskelement>
         <maskelement>
            <mename>specific</mename>
            <mevalue>1025</mevalue>
         </maskelement>
      </mask>
      <uei>uei.opennms.org/vendor/aruba/switch/traps/wlsxFanTrayRemoved</uei>
      <event-label>WLSX-SWITCH-MIB defined trap event: wlsxFanTrayRemoved</event-label>
      <descr>&lt;p>
			A trap which indicates that the fan tray is removed.
			&lt;/p>&lt;table>&lt;/table></descr>
      <logmsg dest="logndisplay">&lt;p>
	wlsxFanTrayRemoved trap received&lt;/p></logmsg>
      <severity>Indeterminate</severity>
   </event>
   <event>
      <mask>
         <maskelement>
            <mename>id</mename>
            <mevalue>.1.3.6.1.4.1.14823.2.2.1.1.100</mevalue>
         </maskelement>
         <maskelement>
            <mename>generic</mename>
            <mevalue>6</mevalue>
         </maskelement>
         <maskelement>
            <mename>specific</mename>
            <mevalue>1026</mevalue>
         </maskelement>
      </mask>
      <uei>uei.opennms.org/vendor/aruba/switch/traps/wlsxFanTrayInserted</uei>
      <event-label>WLSX-SWITCH-MIB defined trap event: wlsxFanTrayInserted</event-label>
      <descr>&lt;p>
			A trap which indicates that the fan tray is removed.
			&lt;/p>&lt;table>&lt;/table></descr>
      <logmsg dest="logndisplay">&lt;p>
	wlsxFanTrayInserted trap received&lt;/p></logmsg>
      <severity>Indeterminate</severity>
   </event>
   <event>
      <mask>
         <maskelement>
            <mename>id</mename>
            <mevalue>.1.3.6.1.4.1.14823.2.2.1.1.100</mevalue>
         </maskelement>
         <maskelement>
            <mename>generic</mename>
            <mevalue>6</mevalue>
         </maskelement>
         <maskelement>
            <mename>specific</mename>
            <mevalue>1027</mevalue>
         </maskelement>
      </mask>
      <uei>uei.opennms.org/vendor/aruba/switch/traps/wlsxLCRemoved</uei>
      <event-label>WLSX-SWITCH-MIB defined trap event: wlsxLCRemoved</event-label>
      <descr>&lt;p>
			A trap which indicates that a Line card is removed.
			&lt;/p>&lt;table>
	&lt;tr>&lt;td>&lt;b>

	wlsxLineCardNumber&lt;/b>&lt;/td>&lt;td>
	%parm[#1]%;&lt;/td>&lt;td>&lt;p>&lt;/p>&lt;/td>&lt;/tr>
	&lt;tr>&lt;td>&lt;b>

	wlsxSlotNumber&lt;/b>&lt;/td>&lt;td>
	%parm[#2]%;&lt;/td>&lt;td>&lt;p>&lt;/p>&lt;/td>&lt;/tr>&lt;/table></descr>
      <logmsg dest="logndisplay">&lt;p>
	wlsxLCRemoved trap received
	wlsxLineCardNumber=%parm[#1]%
	wlsxSlotNumber=%parm[#2]%&lt;/p></logmsg>
      <severity>Indeterminate</severity>
   </event>
   <event>
      <mask>
         <maskelement>
            <mename>id</mename>
            <mevalue>.1.3.6.1.4.1.14823.2.2.1.1.100</mevalue>
         </maskelement>
         <maskelement>
            <mename>generic</mename>
            <mevalue>6</mevalue>
         </maskelement>
         <maskelement>
            <mename>specific</mename>
            <mevalue>1028</mevalue>
         </maskelement>
      </mask>
      <uei>uei.opennms.org/vendor/aruba/switch/traps/wlsxSCRemoved</uei>
      <event-label>WLSX-SWITCH-MIB defined trap event: wlsxSCRemoved</event-label>
      <descr>&lt;p>
			A trap which indicates that a supervisory card is removed.
			&lt;/p>&lt;table>&lt;/table></descr>
      <logmsg dest="logndisplay">&lt;p>
	wlsxSCRemoved trap received&lt;/p></logmsg>
      <severity>Indeterminate</severity>
   </event>
   <event>
      <mask>
         <maskelement>
            <mename>id</mename>
            <mevalue>.1.3.6.1.4.1.14823.2.2.1.1.100</mevalue>
         </maskelement>
         <maskelement>
            <mename>generic</mename>
            <mevalue>6</mevalue>
         </maskelement>
         <maskelement>
            <mename>specific</mename>
            <mevalue>1029</mevalue>
         </maskelement>
      </mask>
      <uei>uei.opennms.org/vendor/aruba/switch/traps/wlsxPowerSupplyMissing</uei>
      <event-label>WLSX-SWITCH-MIB defined trap event: wlsxPowerSupplyMissing</event-label>
      <descr>&lt;p>
			A trap which indicates that the power supply is missing.
			&lt;/p>&lt;table>&lt;/table></descr>
      <logmsg dest="logndisplay">&lt;p>
	wlsxPowerSupplyMissing trap received&lt;/p></logmsg>
      <severity>Indeterminate</severity>
   </event>
   <event>
      <mask>
         <maskelement>
            <mename>id</mename>
            <mevalue>.1.3.6.1.4.1.14823.2.2.1.1.100</mevalue>
         </maskelement>
         <maskelement>
            <mename>generic</mename>
            <mevalue>6</mevalue>
         </maskelement>
         <maskelement>
            <mename>specific</mename>
            <mevalue>1030</mevalue>
         </maskelement>
      </mask>
      <uei>uei.opennms.org/vendor/aruba/switch/traps/wlsxAccessPointIsUp</uei>
      <event-label>WLSX-SWITCH-MIB defined trap event: wlsxAccessPointIsUp</event-label>
      <descr>&lt;p>
			A trap which indicates that an Access point at Location 
			apLocation and Address apIpAddress is up.
			&lt;/p>&lt;table>
	&lt;tr>&lt;td>&lt;b>

	apLocation&lt;/b>&lt;/td>&lt;td>
	%parm[#1]%;&lt;/td>&lt;td>&lt;p>&lt;/p>&lt;/td>&lt;/tr>
	&lt;tr>&lt;td>&lt;b>

	apIpAddress&lt;/b>&lt;/td>&lt;td>
	%parm[#2]%;&lt;/td>&lt;td>&lt;p>&lt;/p>&lt;/td>&lt;/tr>&lt;/table></descr>
      <logmsg dest="logndisplay">&lt;p>
	wlsxAccessPointIsUp trap received
	apLocation=%parm[#1]%
	apIpAddress=%parm[#2]%&lt;/p></logmsg>
      <severity>Indeterminate</severity>
   </event>
   <event>
      <mask>
         <maskelement>
            <mename>id</mename>
            <mevalue>.1.3.6.1.4.1.14823.2.2.1.1.100</mevalue>
         </maskelement>
         <maskelement>
            <mename>generic</mename>
            <mevalue>6</mevalue>
         </maskelement>
         <maskelement>
            <mename>specific</mename>
            <mevalue>1031</mevalue>
         </maskelement>
      </mask>
      <uei>uei.opennms.org/vendor/aruba/switch/traps/wlsxAccessPointIsDown</uei>
      <event-label>WLSX-SWITCH-MIB defined trap event: wlsxAccessPointIsDown</event-label>
      <descr>&lt;p>
			A trap which indicates that an Access point at Location 
			apLocation and Address apIpAddress is down.
			&lt;/p>&lt;table>
	&lt;tr>&lt;td>&lt;b>

	apLocation&lt;/b>&lt;/td>&lt;td>
	%parm[#1]%;&lt;/td>&lt;td>&lt;p>&lt;/p>&lt;/td>&lt;/tr>
	&lt;tr>&lt;td>&lt;b>

	apIpAddress&lt;/b>&lt;/td>&lt;td>
	%parm[#2]%;&lt;/td>&lt;td>&lt;p>&lt;/p>&lt;/td>&lt;/tr>&lt;/table></descr>
      <logmsg dest="logndisplay">&lt;p>
	wlsxAccessPointIsDown trap received
	apLocation=%parm[#1]%
	apIpAddress=%parm[#2]%&lt;/p></logmsg>
      <severity>Indeterminate</severity>
   </event>
   <event>
      <mask>
         <maskelement>
            <mename>id</mename>
            <mevalue>.1.3.6.1.4.1.14823.2.2.1.1.100</mevalue>
         </maskelement>
         <maskelement>
            <mename>generic</mename>
            <mevalue>6</mevalue>
         </maskelement>
         <maskelement>
            <mename>specific</mename>
            <mevalue>1032</mevalue>
         </maskelement>
      </mask>
      <uei>uei.opennms.org/vendor/aruba/switch/traps/wlsxCoverageHoleDetected</uei>
      <event-label>WLSX-SWITCH-MIB defined trap event: wlsxCoverageHoleDetected</event-label>
      <descr>&lt;p>
			A trap which indicates that an Access point at Location
			apLocation and Address apIpAddress has detected a Coverage Hole.
			&lt;/p>&lt;table>
	&lt;tr>&lt;td>&lt;b>

	apLocation&lt;/b>&lt;/td>&lt;td>
	%parm[#1]%;&lt;/td>&lt;td>&lt;p>&lt;/p>&lt;/td>&lt;/tr>
	&lt;tr>&lt;td>&lt;b>

	apIpAddress&lt;/b>&lt;/td>&lt;td>
	%parm[#2]%;&lt;/td>&lt;td>&lt;p>&lt;/p>&lt;/td>&lt;/tr>
	&lt;tr>&lt;td>&lt;b>

	wlsxStationMacAddress&lt;/b>&lt;/td>&lt;td>
	%parm[#3]%;&lt;/td>&lt;td>&lt;p>&lt;/p>&lt;/td>&lt;/tr>&lt;/table></descr>
      <logmsg dest="logndisplay">&lt;p>
	wlsxCoverageHoleDetected trap received
	apLocation=%parm[#1]%
	apIpAddress=%parm[#2]%
	wlsxStationMacAddress=%parm[#3]%&lt;/p></logmsg>
      <severity>Indeterminate</severity>
   </event>
   <event>
      <mask>
         <maskelement>
            <mename>id</mename>
            <mevalue>.1.3.6.1.4.1.14823.2.2.1.1.100</mevalue>
         </maskelement>
         <maskelement>
            <mename>generic</mename>
            <mevalue>6</mevalue>
         </maskelement>
         <maskelement>
            <mename>specific</mename>
            <mevalue>1033</mevalue>
         </maskelement>
      </mask>
      <uei>uei.opennms.org/vendor/aruba/switch/traps/wlsxChannelChanged</uei>
      <event-label>WLSX-SWITCH-MIB defined trap event: wlsxChannelChanged</event-label>
      <descr>&lt;p>
			A trap which indicates that an Access point at Location 
			apLocation and Address apIpAddress has changed the channel to 
			apCurrentChannel.
			&lt;/p>&lt;table>
	&lt;tr>&lt;td>&lt;b>

	apLocation&lt;/b>&lt;/td>&lt;td>
	%parm[#1]%;&lt;/td>&lt;td>&lt;p>&lt;/p>&lt;/td>&lt;/tr>
	&lt;tr>&lt;td>&lt;b>

	apIpAddress&lt;/b>&lt;/td>&lt;td>
	%parm[#2]%;&lt;/td>&lt;td>&lt;p>&lt;/p>&lt;/td>&lt;/tr>
	&lt;tr>&lt;td>&lt;b>

	apCurrentChannel&lt;/b>&lt;/td>&lt;td>
	%parm[#3]%;&lt;/td>&lt;td>&lt;p>&lt;/p>&lt;/td>&lt;/tr>&lt;/table></descr>
      <logmsg dest="logndisplay">&lt;p>
	wlsxChannelChanged trap received
	apLocation=%parm[#1]%
	apIpAddress=%parm[#2]%
	apCurrentChannel=%parm[#3]%&lt;/p></logmsg>
      <severity>Indeterminate</severity>
   </event>
   <event>
      <mask>
         <maskelement>
            <mename>id</mename>
            <mevalue>.1.3.6.1.4.1.14823.2.2.1.1.100</mevalue>
         </maskelement>
         <maskelement>
            <mename>generic</mename>
            <mevalue>6</mevalue>
         </maskelement>
         <maskelement>
            <mename>specific</mename>
            <mevalue>1034</mevalue>
         </maskelement>
      </mask>
      <uei>uei.opennms.org/vendor/aruba/switch/traps/wlsxStationAddedToBlackList</uei>
      <event-label>WLSX-SWITCH-MIB defined trap event: wlsxStationAddedToBlackList</event-label>
      <descr>&lt;p>
			A trap which indicates that a station with address
			wlsxStationMacAddress is black listed for 
			wlsxStationBlackListReason reason.
			&lt;/p>&lt;table>
	&lt;tr>&lt;td>&lt;b>

	wlsxStationMacAddress&lt;/b>&lt;/td>&lt;td>
	%parm[#1]%;&lt;/td>&lt;td>&lt;p>&lt;/p>&lt;/td>&lt;/tr>
	&lt;tr>&lt;td>&lt;b>

	wlsxStationBlackListReason&lt;/b>&lt;/td>&lt;td>
	%parm[#2]%;&lt;/td>&lt;td>&lt;p>
		userDefined(1)
		mitmAttack(2)
		authFailure(3)
		pingFlood(4)
		sessionFlood(5)
		synFlood(6)
		sessionBlacklist(7)
		ipSpoofing(8)
		other(100)
	&lt;/p>&lt;/td>&lt;/tr>&lt;/table></descr>
      <logmsg dest="logndisplay">&lt;p>
	wlsxStationAddedToBlackList trap received
	wlsxStationMacAddress=%parm[#1]%
	wlsxStationBlackListReason=%parm[#2]%&lt;/p></logmsg>
      <severity>Indeterminate</severity>
      <varbindsdecode>
         <parmid>parm[#2]</parmid>
         <decode varbindvalue="1" varbinddecodedstring="userDefined"/>
         <decode varbindvalue="2" varbinddecodedstring="mitmAttack"/>
         <decode varbindvalue="3" varbinddecodedstring="authFailure"/>
         <decode varbindvalue="4" varbinddecodedstring="pingFlood"/>
         <decode varbindvalue="5" varbinddecodedstring="sessionFlood"/>
         <decode varbindvalue="6" varbinddecodedstring="synFlood"/>
         <decode varbindvalue="7" varbinddecodedstring="sessionBlacklist"/>
         <decode varbindvalue="8" varbinddecodedstring="ipSpoofing"/>
         <decode varbindvalue="100" varbinddecodedstring="other"/>
      </varbindsdecode>
   </event>
   <event>
      <mask>
         <maskelement>
            <mename>id</mename>
            <mevalue>.1.3.6.1.4.1.14823.2.2.1.1.100</mevalue>
         </maskelement>
         <maskelement>
            <mename>generic</mename>
            <mevalue>6</mevalue>
         </maskelement>
         <maskelement>
            <mename>specific</mename>
            <mevalue>1035</mevalue>
         </maskelement>
      </mask>
      <uei>uei.opennms.org/vendor/aruba/switch/traps/wlsxStationRemovedFromBlackList</uei>
      <event-label>WLSX-SWITCH-MIB defined trap event: wlsxStationRemovedFromBlackList</event-label>
      <descr>&lt;p>
			A trap which indicates that a station with address
			wlsxStationMacAddress is removed from black list.
			&lt;/p>&lt;table>
	&lt;tr>&lt;td>&lt;b>

	wlsxStationMacAddress&lt;/b>&lt;/td>&lt;td>
	%parm[#1]%;&lt;/td>&lt;td>&lt;p>&lt;/p>&lt;/td>&lt;/tr>&lt;/table></descr>
      <logmsg dest="logndisplay">&lt;p>
	wlsxStationRemovedFromBlackList trap received
	wlsxStationMacAddress=%parm[#1]%&lt;/p></logmsg>
      <severity>Indeterminate</severity>
   </event>
   <event>
      <mask>
         <maskelement>
            <mename>id</mename>
            <mevalue>.1.3.6.1.4.1.14823.2.2.1.1.100</mevalue>
         </maskelement>
         <maskelement>
            <mename>generic</mename>
            <mevalue>6</mevalue>
         </maskelement>
         <maskelement>
            <mename>specific</mename>
            <mevalue>1036</mevalue>
         </maskelement>
      </mask>
      <uei>uei.opennms.org/vendor/aruba/switch/traps/wlsxIpSpoofingDetected</uei>
      <event-label>WLSX-SWITCH-MIB defined trap event: wlsxIpSpoofingDetected</event-label>
      <descr>&lt;p>
			A trap indicating that the switch detected IP Spoofing.
			&lt;/p>&lt;table>
	&lt;tr>&lt;td>&lt;b>

	wlsxSpoofedIpAddress&lt;/b>&lt;/td>&lt;td>
	%parm[#1]%;&lt;/td>&lt;td>&lt;p>&lt;/p>&lt;/td>&lt;/tr>
	&lt;tr>&lt;td>&lt;b>

	wlsxSpoofedOldPhyAddress&lt;/b>&lt;/td>&lt;td>
	%parm[#2]%;&lt;/td>&lt;td>&lt;p>&lt;/p>&lt;/td>&lt;/tr>
	&lt;tr>&lt;td>&lt;b>

	wlsxSpoofedNewPhyAddress&lt;/b>&lt;/td>&lt;td>
	%parm[#3]%;&lt;/td>&lt;td>&lt;p>&lt;/p>&lt;/td>&lt;/tr>&lt;/table></descr>
      <logmsg dest="logndisplay">&lt;p>
	wlsxIpSpoofingDetected trap received
	wlsxSpoofedIpAddress=%parm[#1]%
	wlsxSpoofedOldPhyAddress=%parm[#2]%
	wlsxSpoofedNewPhyAddress=%parm[#3]%&lt;/p></logmsg>
      <severity>Indeterminate</severity>
   </event>
   <event>
      <mask>
         <maskelement>
            <mename>id</mename>
            <mevalue>.1.3.6.1.4.1.14823.2.2.1.1.100</mevalue>
         </maskelement>
         <maskelement>
            <mename>generic</mename>
            <mevalue>6</mevalue>
         </maskelement>
         <maskelement>
            <mename>specific</mename>
            <mevalue>1037</mevalue>
         </maskelement>
      </mask>
      <uei>uei.opennms.org/vendor/aruba/switch/traps/wlsxDBCommunicationFailure</uei>
      <event-label>WLSX-SWITCH-MIB defined trap event: wlsxDBCommunicationFailure</event-label>
      <descr>&lt;p>
			A trap to indicate that communication with Database failed.
			&lt;/p>&lt;table>
	&lt;tr>&lt;td>&lt;b>

	wlsxDBName&lt;/b>&lt;/td>&lt;td>
	%parm[#1]%;&lt;/td>&lt;td>&lt;p>&lt;/p>&lt;/td>&lt;/tr>
	&lt;tr>&lt;td>&lt;b>

	wlsxDBUserName&lt;/b>&lt;/td>&lt;td>
	%parm[#2]%;&lt;/td>&lt;td>&lt;p>&lt;/p>&lt;/td>&lt;/tr>
	&lt;tr>&lt;td>&lt;b>

	wlsxDBIpAddress&lt;/b>&lt;/td>&lt;td>
	%parm[#3]%;&lt;/td>&lt;td>&lt;p>&lt;/p>&lt;/td>&lt;/tr>
	&lt;tr>&lt;td>&lt;b>

	wlsxDBType&lt;/b>&lt;/td>&lt;td>
	%parm[#4]%;&lt;/td>&lt;td>&lt;p>
		mssql(1)
		mysql(2)
	&lt;/p>&lt;/td>&lt;/tr>&lt;/table></descr>
      <logmsg dest="logndisplay">&lt;p>
	wlsxDBCommunicationFailure trap received
	wlsxDBName=%parm[#1]%
	wlsxDBUserName=%parm[#2]%
	wlsxDBIpAddress=%parm[#3]%
	wlsxDBType=%parm[#4]%&lt;/p></logmsg>
      <severity>Indeterminate</severity>
      <varbindsdecode>
         <parmid>parm[#4]</parmid>
         <decode varbindvalue="1" varbinddecodedstring="mssql"/>
         <decode varbindvalue="2" varbinddecodedstring="mysql"/>
      </varbindsdecode>
   </event>
   <event>
      <mask>
         <maskelement>
            <mename>id</mename>
            <mevalue>.1.3.6.1.4.1.14823.2.2.1.1.100</mevalue>
         </maskelement>
         <maskelement>
            <mename>generic</mename>
            <mevalue>6</mevalue>
         </maskelement>
         <maskelement>
            <mename>specific</mename>
            <mevalue>1038</mevalue>
         </maskelement>
      </mask>
      <uei>uei.opennms.org/vendor/aruba/switch/traps/wlsxVrrpStateChange</uei>
      <event-label>WLSX-SWITCH-MIB defined trap event: wlsxVrrpStateChange</event-label>
      <descr>&lt;p>
				A trap which indicates that VRRP State has changed on the switch.
			&lt;/p>&lt;table>
	&lt;tr>&lt;td>&lt;b>

	wlsxVrID&lt;/b>&lt;/td>&lt;td>
	%parm[#1]%;&lt;/td>&lt;td>&lt;p>&lt;/p>&lt;/td>&lt;/tr>
	&lt;tr>&lt;td>&lt;b>

	wlsxVrMasterIp&lt;/b>&lt;/td>&lt;td>
	%parm[#2]%;&lt;/td>&lt;td>&lt;p>&lt;/p>&lt;/td>&lt;/tr>
	&lt;tr>&lt;td>&lt;b>

	wlsxVrrpOperState&lt;/b>&lt;/td>&lt;td>
	%parm[#3]%;&lt;/td>&lt;td>&lt;p>
		initialize(1)
		backup(2)
		master(3)
	&lt;/p>&lt;/td>&lt;/tr>&lt;/table></descr>
      <logmsg dest="logndisplay">&lt;p>
	wlsxVrrpStateChange trap received
	wlsxVrID=%parm[#1]%
	wlsxVrMasterIp=%parm[#2]%
	wlsxVrrpOperState=%parm[#3]%&lt;/p></logmsg>
      <severity>Indeterminate</severity>
      <varbindsdecode>
         <parmid>parm[#3]</parmid>
         <decode varbindvalue="1" varbinddecodedstring="initialize"/>
         <decode varbindvalue="2" varbinddecodedstring="backup"/>
         <decode varbindvalue="3" varbinddecodedstring="master"/>
      </varbindsdecode>
   </event>
   <event>
      <mask>
         <maskelement>
            <mename>id</mename>
            <mevalue>.1.3.6.1.4.1.14823.2.2.1.1.100</mevalue>
         </maskelement>
         <maskelement>
            <mename>generic</mename>
            <mevalue>6</mevalue>
         </maskelement>
         <maskelement>
            <mename>specific</mename>
            <mevalue>1039</mevalue>
         </maskelement>
      </mask>
      <uei>uei.opennms.org/vendor/aruba/switch/traps/wlsxAPRadioAttributesChanged</uei>
      <event-label>WLSX-SWITCH-MIB defined trap event: wlsxAPRadioAttributesChanged</event-label>
      <descr>&lt;p>
			A trap which indicates changes in the Radio attributes of an 
			Access Point at location apLocation and address apIpAddress.
			Ap channel is apCurrentChannel, and Transmit power is 
			apTxPower.
			&lt;/p>&lt;table>
	&lt;tr>&lt;td>&lt;b>

	apLocation&lt;/b>&lt;/td>&lt;td>
	%parm[#1]%;&lt;/td>&lt;td>&lt;p>&lt;/p>&lt;/td>&lt;/tr>
	&lt;tr>&lt;td>&lt;b>

	apIpAddress&lt;/b>&lt;/td>&lt;td>
	%parm[#2]%;&lt;/td>&lt;td>&lt;p>&lt;/p>&lt;/td>&lt;/tr>
	&lt;tr>&lt;td>&lt;b>

	apCurrentChannel&lt;/b>&lt;/td>&lt;td>
	%parm[#3]%;&lt;/td>&lt;td>&lt;p>&lt;/p>&lt;/td>&lt;/tr>
	&lt;tr>&lt;td>&lt;b>

	wlsxApTxPower&lt;/b>&lt;/td>&lt;td>
	%parm[#4]%;&lt;/td>&lt;td>&lt;p>&lt;/p>&lt;/td>&lt;/tr>&lt;/table></descr>
      <logmsg dest="logndisplay">&lt;p>
	wlsxAPRadioAttributesChanged trap received
	apLocation=%parm[#1]%
	apIpAddress=%parm[#2]%
	apCurrentChannel=%parm[#3]%
	wlsxApTxPower=%parm[#4]%&lt;/p></logmsg>
      <severity>Indeterminate</severity>
   </event>
   <event>
      <mask>
         <maskelement>
            <mename>id</mename>
            <mevalue>.1.3.6.1.4.1.14823.2.2.1.1.100</mevalue>
         </maskelement>
         <maskelement>
            <mename>generic</mename>
            <mevalue>6</mevalue>
         </maskelement>
         <maskelement>
            <mename>specific</mename>
            <mevalue>1040</mevalue>
         </maskelement>
      </mask>
      <uei>uei.opennms.org/vendor/aruba/switch/traps/wlsxESIServerUp</uei>
      <event-label>WLSX-SWITCH-MIB defined trap event: wlsxESIServerUp</event-label>
      <descr>&lt;p>
			A trap which indicates that a ESI server &lt;wlsxESIServerName> in 
			group &lt;wlsxESIServerGrpName> with &lt;wlsxESIServerIpaddress> is up
			&lt;/p>&lt;table>
	&lt;tr>&lt;td>&lt;b>

	wlsxESIServerGrpName&lt;/b>&lt;/td>&lt;td>
	%parm[#1]%;&lt;/td>&lt;td>&lt;p>&lt;/p>&lt;/td>&lt;/tr>
	&lt;tr>&lt;td>&lt;b>

	wlsxESIServerName&lt;/b>&lt;/td>&lt;td>
	%parm[#2]%;&lt;/td>&lt;td>&lt;p>&lt;/p>&lt;/td>&lt;/tr>
	&lt;tr>&lt;td>&lt;b>

	wlsxESIServerIpaddress&lt;/b>&lt;/td>&lt;td>
	%parm[#3]%;&lt;/td>&lt;td>&lt;p>&lt;/p>&lt;/td>&lt;/tr>&lt;/table></descr>
      <logmsg dest="logndisplay">&lt;p>
	wlsxESIServerUp trap received
	wlsxESIServerGrpName=%parm[#1]%
	wlsxESIServerName=%parm[#2]%
	wlsxESIServerIpaddress=%parm[#3]%&lt;/p></logmsg>
      <severity>Indeterminate</severity>
   </event>
   <event>
      <mask>
         <maskelement>
            <mename>id</mename>
            <mevalue>.1.3.6.1.4.1.14823.2.2.1.1.100</mevalue>
         </maskelement>
         <maskelement>
            <mename>generic</mename>
            <mevalue>6</mevalue>
         </maskelement>
         <maskelement>
            <mename>specific</mename>
            <mevalue>1041</mevalue>
         </maskelement>
      </mask>
      <uei>uei.opennms.org/vendor/aruba/switch/traps/wlsxESIServerDown</uei>
      <event-label>WLSX-SWITCH-MIB defined trap event: wlsxESIServerDown</event-label>
      <descr>&lt;p>
			A trap which indicates that a ESI server &lt;wlsxESIServerName> in 
			group &lt;wlsxESIServerGrpName> with &lt;wlsxESIServerIpaddress> is down
			&lt;/p>&lt;table>
	&lt;tr>&lt;td>&lt;b>

	wlsxESIServerGrpName&lt;/b>&lt;/td>&lt;td>
	%parm[#1]%;&lt;/td>&lt;td>&lt;p>&lt;/p>&lt;/td>&lt;/tr>
	&lt;tr>&lt;td>&lt;b>

	wlsxESIServerName&lt;/b>&lt;/td>&lt;td>
	%parm[#2]%;&lt;/td>&lt;td>&lt;p>&lt;/p>&lt;/td>&lt;/tr>
	&lt;tr>&lt;td>&lt;b>

	wlsxESIServerIpaddress&lt;/b>&lt;/td>&lt;td>
	%parm[#3]%;&lt;/td>&lt;td>&lt;p>&lt;/p>&lt;/td>&lt;/tr>&lt;/table></descr>
      <logmsg dest="logndisplay">&lt;p>
	wlsxESIServerDown trap received
	wlsxESIServerGrpName=%parm[#1]%
	wlsxESIServerName=%parm[#2]%
	wlsxESIServerIpaddress=%parm[#3]%&lt;/p></logmsg>
      <severity>Indeterminate</severity>
   </event>
   <event>
      <mask>
         <maskelement>
            <mename>id</mename>
            <mevalue>.1.3.6.1.4.1.14823.2.2.1.1.100</mevalue>
         </maskelement>
         <maskelement>
            <mename>generic</mename>
            <mevalue>6</mevalue>
         </maskelement>
         <maskelement>
            <mename>specific</mename>
            <mevalue>1042</mevalue>
         </maskelement>
      </mask>
      <uei>uei.opennms.org/vendor/aruba/switch/traps/wlsxLicenseExpiry</uei>
      <event-label>WLSX-SWITCH-MIB defined trap event: wlsxLicenseExpiry</event-label>
      <descr>&lt;p>
			A trap which indicates that one or more licenses on the
			switch will expire in &lt;wlsxLicenseDaysRemaining> days
			&lt;/p>&lt;table>
	&lt;tr>&lt;td>&lt;b>

	wlsxLicenseDaysRemaining&lt;/b>&lt;/td>&lt;td>
	%parm[#1]%;&lt;/td>&lt;td>&lt;p>&lt;/p>&lt;/td>&lt;/tr>&lt;/table></descr>
      <logmsg dest="logndisplay">&lt;p>
	wlsxLicenseExpiry trap received
	wlsxLicenseDaysRemaining=%parm[#1]%&lt;/p></logmsg>
      <severity>Indeterminate</severity>
   </event>
</events>